[
    {
        "id": "tile_001",
        "title": "Ceramic Blue Tile",
        "description": "Premium ceramic tile with a smooth blue glaze finish, perfect for bathroom walls.",
        "image": "/images/tiles/tile_001.jpg",
        "category": "ceramic",
        "price": 45.99,
        "currency": "USD",
        "dimensions": "60x60 cm",
        "material": "Ceramic",
        "inStock": true
    },
    {
        "id": "tile_002",
        "title": "Marble Carrara White",
        "description": "Elegant white marble tile with grey veining for a luxurious floor look.",
        "image": "/images/tiles/tile_002.jpg",
        "category": "marble",
        "price": 89.50,
        "currency": "USD",
        "dimensions": "60x120 cm",
        "material": "Natural Marble",
        "inStock": true
    },
    {
        "id": "tile_003",
        "title": "Matte Slate Grey",
        "description": "Durable porcelain tile with a slip-resistant matte finish for outdoor patios.",
        "image": "/images/tiles/tile_003.jpg",
        "category": "porcelain",
        "price": 32.25,
        "currency": "USD",
        "dimensions": "30x60 cm",
        "material": "Porcelain",
        "inStock": true
    },
    {
        "id": "tile_004",
        "title": "Emerald Glass Mosaic",
        "description": "Handcrafted glass mosaic tiles in vibrant emerald green for backsplash accents.",
        "image": "/images/tiles/tile_004.jpg",
        "category": "glass",
        "price": 12.99,
        "currency": "USD",
        "dimensions": "30x30 cm",
        "material": "Glass",
        "inStock": true
    },
    {
        "id": "tile_005",
        "title": "Rustic Terracotta",
        "description": "Traditional kiln-fired terracotta tiles offering a warm, earthy aesthetic.",
        "image": "/images/tiles/tile_005.jpg",
        "category": "terracotta",
        "price": 28.00,
        "currency": "USD",
        "dimensions": "40x40 cm",
        "material": "Clay",
        "inStock": false
    },
    {
        "id": "tile_006",
        "title": "Travertine Beige",
        "description": "Natural stone travertine with a tumbled finish for a rustic indoor feel.",
        "image": "/images/tiles/tile_006.jpg",
        "category": "stone",
        "price": 55.75,
        "currency": "USD",
        "dimensions": "45x45 cm",
        "material": "Travertine",
        "inStock": true
    },
    {
        "id": "tile_007",
        "title": "Polished Onyx Black",
        "description": "High-gloss black porcelain tile with deep reflective properties.",
        "image": "/images/tiles/tile_007.jpg",
        "category": "porcelain",
        "price": 62.40,
        "currency": "USD",
        "dimensions": "80x80 cm",
        "material": "Porcelain",
        "inStock": true
    },
    {
        "id": "tile_008",
        "title": "Wood-Look Plank",
        "description": "Porcelain tiles that mimic the natural texture and color of oak wood planks.",
        "image": "/images/tiles/tile_008.jpg",
        "category": "wood-look",
        "price": 38.90,
        "currency": "USD",
        "dimensions": "20x120 cm",
        "material": "Porcelain",
        "inStock": true
    },
    {
        "id": "tile_009",
        "title": "Geometric Cement Tile",
        "description": "Artisan cement tiles featuring a modern black and white geometric pattern.",
        "image": "/images/tiles/tile_009.jpg",
        "category": "cement",
        "price": 18.50,
        "currency": "USD",
        "dimensions": "20x20 cm",
        "material": "Cement",
        "inStock": true
    },
    {
        "id": "tile_010",
        "title": "Subway Gloss White",
        "description": "Classic beveled-edge subway tile for a timeless kitchen backsplash.",
        "image": "/images/tiles/tile_010.jpg",
        "category": "ceramic",
        "price": 22.00,
        "currency": "USD",
        "dimensions": "10x30 cm",
        "material": "Ceramic",
        "inStock": true
    },
    {
        "id": "tile_011",
        "title": "Granite Speckled Grey",
        "description": "Industrial-grade granite tile, highly resistant to heavy foot traffic.",
        "image": "/images/tiles/tile_011.jpg",
        "category": "stone",
        "price": 74.30,
        "currency": "USD",
        "dimensions": "60x60 cm",
        "material": "Granite",
        "inStock": true
    },
    {
        "id": "tile_012",
        "title": "Victorian Floral Pattern",
        "description": "Decorative ceramic tile with an intricate vintage floral print.",
        "image": "/images/tiles/tile_012.jpg",
        "category": "decorative",
        "price": 15.20,
        "currency": "USD",
        "dimensions": "15x15 cm",
        "material": "Ceramic",
        "inStock": false
    }
]
